reinventing_catastrophe_modelling/__init__.py
reinventing_catastrophe_modelling/__main__.py
reinventing_catastrophe_modelling/bootstrap.py
reinventing_catastrophe_modelling/cli/load_ee_cli.py
reinventing_catastrophe_modelling/config/model_settings.py
reinventing_catastrophe_modelling/src/__init__.py
reinventing_catastrophe_modelling/src/generate_building_centroids.py
reinventing_catastrophe_modelling/src/get_google_streetview.py
reinventing_catastrophe_modelling/src/load_ee_data.py
reinventing_catastrophe_modelling/utils/utils.py
reinventing_catastrophe_modelling-0.1.2.dist-info/WHEEL
reinventing_catastrophe_modelling-0.1.2.dist-info/METADATA
reinventing_catastrophe_modelling-0.1.2.dist-info/RECORD
