Metadata-Version: 2.1
Name: reinventing-catastrophe-modelling
Version: 0.1.2
Summary: 
Author: ChristinaLast
Author-email: christina.last@outlook.com
Requires-Python: >=3.8,<4.0
Classifier: Programming Language :: Python :: 3
Classifier: Programming Language :: Python :: 3.10
Classifier: Programming Language :: Python :: 3.8
Classifier: Programming Language :: Python :: 3.9
Requires-Dist: Django (>=3.2.6,<4.0.0)
Requires-Dist: PyYAML (>=5.4.1,<6.0.0)
Requires-Dist: bandit (>=1.7.0,<2.0.0)
Requires-Dist: black (>=21.7b0,<22.0)
Requires-Dist: catboost (>=0.26.1,<0.27.0)
Requires-Dist: click-config-file (>=0.6.0,<0.7.0)
Requires-Dist: click-option-group (>=0.5.3,<0.6.0)
Requires-Dist: earthengine-api (>=0.1.280,<0.2.0)
Requires-Dist: esda (>=2.4.1,<3.0.0)
Requires-Dist: geopandas (>=0.9.0,<0.10.0)
Requires-Dist: google (>=3.0.0,<4.0.0)
Requires-Dist: google-streetview (>=1.2.9,<2.0.0)
Requires-Dist: hydra-core (>=1.1.1,<2.0.0)
Requires-Dist: joblib (>=1.0.1,<2.0.0)
Requires-Dist: keplergl (>=0.3.2,<0.4.0)
Requires-Dist: libpysal (>=4.5.1,<5.0.0)
Requires-Dist: loguru (>=0.5.3,<0.6.0)
Requires-Dist: mlflow (>=1.20.1,<2.0.0)
Requires-Dist: osmnx (>=1.1.1,<2.0.0)
Requires-Dist: pydantic (>=1.8.2,<2.0.0)
Requires-Dist: pylama (>=7.7.1,<8.0.0)
Requires-Dist: setuptools (>=57.4.0,<58.0.0)
Requires-Dist: sklearn (>=0.0,<0.1)
